putty.settings-1.0.0-py3.6-nspkg.pth
putty/settings/__init__.py
putty/settings/ssh_host_keys/__init__.py
putty.settings-1.0.0.dist-info/DESCRIPTION.rst
putty.settings-1.0.0.dist-info/METADATA
putty.settings-1.0.0.dist-info/RECORD
putty.settings-1.0.0.dist-info/WHEEL
putty.settings-1.0.0.dist-info/metadata.json
putty.settings-1.0.0.dist-info/namespace_packages.txt
putty.settings-1.0.0.dist-info/top_level.txt
